LICENSE
README.md
setup.py
wapi/__init__.py
wapi/features/DELETE.py
wapi/features/GET.py
wapi/features/PATCH.py
wapi/features/POST.py
wapi/features/PUT.py
wapi/features/Route.py
wapi/features/__init__.py
wapi/features/request.py
wapi/static/T.py
wapi/static/__init__.py
wapi/static/methods.py
wapi/static/params.py
wapi/utils/__init__.py
wapi/utils/get_path.py
wapi/utils/get_used_vars.py
wapi/utils/is_class.py
wapi/utils/is_dataclass.py
wapi/utils/is_object.py
wapi/utils/merge_paths.py
wapi/utils/set_path.py
whaox_wapi.egg-info/PKG-INFO
whaox_wapi.egg-info/SOURCES.txt
whaox_wapi.egg-info/dependency_links.txt
whaox_wapi.egg-info/requires.txt
whaox_wapi.egg-info/top_level.txt