Metadata-Version: 2.1
Name: whaox-wapi
Version: 1.1.0
Summary: Web-Library for Python
Home-page: https://github.com/topanim/WApi
Author: WHAOX
Author-email: gorogannisan641@gmail.com
License: MIT LICENSE, see LICENSE file
Keywords: python,web,api,requests,post,get,put,patch,delete,rest
License-File: LICENSE
Requires-Dist: jsons
Requires-Dist: requests
